LICENSE
README.md
setup.py
pterminal/__init__.py
pterminal/ptl_dispatcher.py
pterminal/ptl_signal.py
pterminal/ptl_thread.py
pterminal.egg-info/PKG-INFO
pterminal.egg-info/SOURCES.txt
pterminal.egg-info/dependency_links.txt
pterminal.egg-info/top_level.txt