Metadata-Version: 2.1
Name: pterminal
Version: 1.0.1
Summary: UNKNOWN
Home-page: https://github.com/nimlea/pterminal
Author: NimLea
License: UNKNOWN
Platform: UNKNOWN
Classifier: License :: OSI Approved :: GNU Lesser General Public License v3 or later (LGPLv3+)
Classifier: Programming Language :: Python :: 3
